gencsr.py
gencsr-0.1.0.dist-info/LICENSE.txt
gencsr-0.1.0.dist-info/METADATA
gencsr-0.1.0.dist-info/WHEEL
gencsr-0.1.0.dist-info/entry_points.txt
gencsr-0.1.0.dist-info/top_level.txt
gencsr-0.1.0.dist-info/RECORD
