Metadata-Version: 2.1
Name: gencsr
Version: 0.1.0
Author-email: Jonathon Reinhart <jonathon.reinhart@gmail.com>
License: 
Project-URL: repository, https://github.com/JonathonReinhart/gencsr
Requires-Python: >=3.8
License-File: LICENSE.txt
Requires-Dist: cryptography
Requires-Dist: toml
